poetic_errors/__init__.py
poetic_errors/handler.py
poetic_errors-0.1.3.dist-info/LICENSE
poetic_errors-0.1.3.dist-info/METADATA
poetic_errors-0.1.3.dist-info/WHEEL
poetic_errors-0.1.3.dist-info/top_level.txt
poetic_errors-0.1.3.dist-info/RECORD
