Metadata-Version: 2.1
Name: poetic-errors
Version: 0.1.3
Summary: Transform Python errors into delightful poems
Home-page: https://github.com/JugalKothari/poetic-errors
Author: Jugal Kothari
Author-email: jugalprakashk19@gmail.com
Classifier: Programming Language :: Python :: 3
Classifier: Programming Language :: Python :: 3.6
Classifier: Programming Language :: Python :: 3.7
Classifier: Programming Language :: Python :: 3.8
Classifier: Programming Language :: Python :: 3.9
Classifier: Programming Language :: Python :: 3.10
Classifier: License :: OSI Approved :: MIT License
Classifier: Operating System :: OS Independent
Requires-Python: >=3.6
License-File: LICENSE
